README.md
setup.py
integer_gantt/__init__.py
integer_gantt/generate.py
integer_gantt/utils.py
integer_gantt.egg-info/PKG-INFO
integer_gantt.egg-info/SOURCES.txt
integer_gantt.egg-info/dependency_links.txt
integer_gantt.egg-info/requires.txt
integer_gantt.egg-info/top_level.txt