Metadata-Version: 2.1
Name: integer-gantt
Version: 0.0.1.4
Summary: integer-gantt: quick and dirty gantt chart generator.
Home-page: https://github.com/kevinglasson/integer-gantt.git
Author: Kevin Glasson
Author-email: kevinglasson+integer-gantt@gmail.com
License: UNKNOWN
Platform: UNKNOWN
Classifier: Development Status :: 3 - Alpha
Classifier: License :: OSI Approved :: MIT License
Classifier: Intended Audience :: Developers
Classifier: Programming Language :: Python :: 3
Requires-Python: >=3
